diskii/__init__.py
diskii/__main__.py
diskii/addressing.py
diskii/basic/__init__.py
diskii/basic/applesoft/__init__.py
diskii/basic/applesoft/detokenizer.py
diskii/basic/applesoft/tokenizer.py
diskii/basic/applesoft/validator.py
diskii/basic/common.py
diskii/basic/common_validator.py
diskii/basic/integer/__init__.py
diskii/basic/integer/detokenizer.py
diskii/basic/integer/tokenizer.py
diskii/basic/integer/validator.py
diskii/basic/tokens.py
diskii/basic_tokenizer.py
diskii/basic_tokens.py
diskii/cli/__init__.py
diskii/cli/commands/__init__.py
diskii/cli/commands/add.py
diskii/cli/commands/basic.py
diskii/cli/commands/convert.py
diskii/cli/commands/create.py
diskii/cli/commands/extract.py
diskii/cli/commands/info.py
diskii/cli/main.py
diskii/cli/utils.py
diskii/detection.py
diskii/disk_creator.py
diskii/dos32.py
diskii/dos33.py
diskii/dos_ordered_block_reader.py
diskii/dos_writer.py
diskii/exceptions.py
diskii/file_operations.py
diskii/file_reading.py
diskii/file_type_conversion.py
diskii/fileentry.py
diskii/image.py
diskii/prodos.py
diskii/prodos_ordered_sector_reader.py
diskii/prodos_types.py
diskii/prodos_writer.py
diskii-0.2.0.dist-info/LICENSE
diskii-0.2.0.dist-info/METADATA
diskii-0.2.0.dist-info/WHEEL
diskii-0.2.0.dist-info/entry_points.txt
diskii-0.2.0.dist-info/RECORD
