Metadata-Version: 2.3
Name: diskii
Version: 0.2.0
Summary: diskii - Apple II Disk Image Tool & Library
License: ISC
Keywords: apple2,apple-ii,disk-image,prodos,dos33,retro-computing
Author: Seth Kushniryk
Author-email: seth@kushniryk.com
Requires-Python: >=3.13
Classifier: Development Status :: 4 - Beta
Classifier: Intended Audience :: Developers
Classifier: Intended Audience :: End Users/Desktop
Classifier: License :: OSI Approved :: ISC License (ISCL)
Classifier: Operating System :: OS Independent
Classifier: Programming Language :: Python :: 3
Classifier: Programming Language :: Python :: 3.13
Classifier: Topic :: System :: Archiving
Classifier: Topic :: Software Development :: Libraries :: Python Modules
Classifier: Topic :: System :: Filesystems
Project-URL: Bug Reports, https://todo.sr.ht/~sethkush/diskii
Project-URL: Documentation, https://git.sr.ht/~sethkush/diskii/tree/master/item/docs
Project-URL: Homepage, https://git.sr.ht/~sethkush/diskii
Project-URL: Source, https://git.sr.ht/~sethkush/diskii
